lazylfs/__init__.py
lazylfs/cli.py
lazylfs/content.py
lazylfs/location.py
lazylfs/pathutils.py
lazylfs/py.typed
lazylfs/version.py
lazylfs-0.3.5.dist-info/LICENSE
lazylfs-0.3.5.dist-info/METADATA
lazylfs-0.3.5.dist-info/WHEEL
lazylfs-0.3.5.dist-info/entry_points.txt
lazylfs-0.3.5.dist-info/top_level.txt
lazylfs-0.3.5.dist-info/RECORD
