Metadata-Version: 2.1
Name: lazylfs
Version: 0.3.5
Summary: A quick way to version control data stored remotely
Home-page: https://github.com/apljungquist/lazylfs
Author: AP Ljungquist
Author-email: ap@ljungquist.eu
License: UNKNOWN
Platform: UNKNOWN
Classifier: Programming Language :: Python :: 3
Classifier: License :: OSI Approved :: MIT License
Classifier: Operating System :: Unix
Requires-Dist: sprig
Provides-Extra: cli
Requires-Dist: fire ; extra == 'cli'
